MANIFEST.in
README.rst
setup.py
discussion/__init__.py
discussion/admin.py
discussion/forms.py
discussion/models.py
discussion/search_indexes.py
discussion/urls.py
discussion/utils.py
discussion/views.py
discussion/migrations/0001_initial.py
discussion/migrations/0002_auto__add_field_discussion_image.py
discussion/migrations/0003_auto__add_field_discussion_description.py
discussion/migrations/0004_auto__add_field_discussion_sort_order.py
discussion/migrations/__init__.py
discussion/static/discussion/scripts/discussion.js
discussion/static/discussion/styles/discussion.css
discussion/templates/discussion/_comment_detail.html
discussion/templates/discussion/_post_detail.html
discussion/templates/discussion/_post_form_fields.html
discussion/templates/discussion/_search_form.html
discussion/templates/discussion/base.html
discussion/templates/discussion/comment_form.html
discussion/templates/discussion/discussion_detail.html
discussion/templates/discussion/discussion_list.html
discussion/templates/discussion/limit_comments.html
discussion/templates/discussion/post_detail.html
discussion/templates/discussion/post_form.html
discussion/templates/discussion/search.html
discussion/templates/search/indexes/discussion/discussion_text.txt
discussion/templates/search/indexes/discussion/post_text.txt
discussion/templates/search/indexes/discussion/post_title.txt
discussion/templatetags/__init__.py
discussion/templatetags/discussiontags.py
django_discussion.egg-info/PKG-INFO
django_discussion.egg-info/SOURCES.txt
django_discussion.egg-info/dependency_links.txt
django_discussion.egg-info/requires.txt
django_discussion.egg-info/top_level.txt