Metadata-Version: 1.0
Name: django-discussion
Version: 0.6
Summary: UNKNOWN
Home-page: http://incuna.com/
Author: Incuna Ltd
Author-email: dev@incuna.com
License: UNKNOWN
Platform: UNKNOWN
